analysis_model/__init__.py
analysis_model/model.py
feedback_analysis-1.0.0.dist-info/METADATA
feedback_analysis-1.0.0.dist-info/WHEEL
feedback_analysis-1.0.0.dist-info/top_level.txt
feedback_analysis-1.0.0.dist-info/RECORD
