Metadata-Version: 2.1
Name: feedback-analysis
Version: 1.0.0
Summary: classify feedback into 'product aspect', 'customer experience', 'issues'
